{"inkVersion":20,"root":[[{"->":"idle"},["done",{"#f":5,"#n":"g-0"}],null],"done",{"idle":[["ev","str","^Interrogation","/str","/ev",{"*":".^.c-0","flg":4},"ev","str","^OnArrive","/str","/ev",{"*":".^.c-1","flg":4},"ev","str","^OnHoboDiscover","/str","/ev",{"*":".^.c-2","flg":4},"ev","str","^OnLockedDoorInteract","/str","/ev",{"*":".^.c-3","flg":4},"ev","str","^OnLockedDoorInteractMany","/str","/ev",{"*":".^.c-4","flg":4},"ev","str","^OnSeeCat","/str","/ev",{"*":".^.c-5","flg":4},"ev","str","^OnCatRun","/str","/ev",{"*":".^.c-6","flg":4},"ev","str","^OnLureCat","/str","/ev",{"*":".^.c-7","flg":4},"ev","str","^OnKeyGet","/str","/ev",{"*":".^.c-8","flg":4},"ev","str","^OnEnterBackroom","/str","/ev",{"*":".^.c-9","flg":4},"ev","str","^OnPlateDrop","/str","/ev",{"*":".^.c-10","flg":4},{"c-0":["^ ",{"->":"interrogation_1_checkpoint","var":true},"\n",{"#f":5}],"c-1":["^ ",{"->":"event_on_arrive"},"\n",{"#f":5}],"c-2":["^ ",{"->":"event_on_hobo_discover"},"\n",{"#f":5}],"c-3":["^ ",{"->":"event_on_locked_door_interact"},"\n",{"#f":5}],"c-4":["^ ",{"->":"event_on_locked_door_interact_many"},"\n",{"#f":5}],"c-5":["^ ",{"->":"event_on_see_cat"},"\n",{"#f":5}],"c-6":["^ ",{"->":"event_on_cat_run"},"\n",{"#f":5}],"c-7":["^ ",{"->":"event_on_lure_cat"},"\n",{"#f":5}],"c-8":["^ ",{"->":"event_on_key_get"},"\n",{"#f":5}],"c-9":["^ ",{"->":"event_on_enter_backroom"},"\n",{"#f":5}],"c-10":["^ ",{"->":"event_on_plate_drop"},"\n",{"#f":5}]}],{"#f":1}],"event_on_arrive":["^EVA: I can't believe Mario is planning to rat me out. I guess I have to have a \"private session\" with him before he does anything stupid.","\n","^EVA: There's an alley that leads to the back of the bar. I must find a way to get inside.","\n","^Use A/D to move; Left click to interact with items; Press E to pick up items","\n",{"->":"end_interrogation"},{"#f":1}],"event_on_hobo_discover":["^EVA: A sleeping hobo, fitting for such a dinghy place","\n",{"->":"end_interrogation"},{"#f":1}],"event_on_locked_door_interact":["^EVA: ",["ev","visit",3,"seq","/ev","ev","du",0,"==","/ev",{"->":".^.s0","c":true},"ev","du",1,"==","/ev",{"->":".^.s1","c":true},"ev","du",2,"==","/ev",{"->":".^.s2","c":true},"nop",{"s0":["pop","^Tchh... the door is locked",{"->":".^.^.23"},null],"s1":["pop","^I need a key to open it",{"->":".^.^.23"},null],"s2":["pop","^It won't budge",{"->":".^.^.23"},null],"#f":5}],"\n",{"->":"end_interrogation"},{"#f":1}],"event_on_locked_door_interact_many":["^EVA: This is getting old.","\n",{"->":"end_interrogation"},{"#f":1}],"event_on_see_cat":["^EVA: I heard its a bad omen to see a black cat.","\n",{"->":"end_interrogation"},{"#f":1}],"event_on_cat_run":["^EVA: Wait, was that... something shiny on its neck?","\n",{"->":"end_interrogation"},{"#f":1}],"event_on_lure_cat":["^EVA: Come here kitty, don't be shy.","\n",{"->":"end_interrogation"},{"#f":1}],"event_on_key_get":["^EVA: Ohh, you are my lucky star.","\n",{"->":"end_interrogation"},{"#f":1}],"event_on_enter_backroom":["^EVA: Urgh, when was the last time they cleaned this room?","\n",{"->":"end_interrogation"},{"#f":1}],"event_on_plate_drop":["^EVA: Here goes nothing!","\n",{"->":"end_interrogation"},{"#f":1}],"interrogation_1":[["^It's a homeless man, who has clearly been weathered by the years. Speak with him?","\n","ev","str","^Yes","/str","/ev",{"*":".^.c-0","flg":4},"ev","str","^No","/str","/ev",{"*":".^.c-1","flg":4},{"c-0":["^ ",{"->":"_interrogation_start"},"\n",{"#f":5}],"c-1":["^ ",{"->":"end_interrogation"},"\n",{"#f":5}]}],{"#f":3}],"_interrogation_start":[["ev","str","^Hello.","/str","/ev",{"*":".^.c-0","flg":4},"ev","str","^Hey, you there?","/str","/ev",{"*":".^.c-1","flg":4},{"c-0":["\n",[["^EVA: Hello.","\n",{"->":".^.^.^.^.g-0"},{"#f":5,"#n":"g-0"}],null],{"#f":5}],"c-1":["\n",[["^EVA: Hey, you there?","\n",{"->":".^.^.^.^.g-0"},{"#f":5,"#n":"g-0"}],null],{"#f":5}],"g-0":["^HOBO: zzz... zzz...","\n","ev","str","^*Gently tap shoulder.*","/str","/ev",{"*":".^.c-2","flg":4},"ev","str","^Can you hear me? C'mon, wake up.","/str","/ev",{"*":".^.c-3","flg":4},{"c-2":["\n",[["^EVA: *gently taps his shoulder*","\n",["^HOBO: *rolls over*","\n",["^EVA: *tap tap tap*","\n",{"->":".^.^.^.^.^.^.^.g-1"},{"#f":5,"#n":"g-2"}],{"#f":5,"#n":"g-1"}],{"#f":5,"#n":"g-0"}],null],{"#f":5}],"c-3":["\n",[["^EVA: Can you hear me? C'mon, wake up.","\n",{"->":".^.^.^.^.^.g-1"},{"#f":5,"#n":"g-0"}],null],{"#f":5}],"#f":5}],"g-1":["^HOBO: Alriiiight, alriiiight, I'm awaaaaake. Whaddoya wan?","\n","ev","str","^Hey, are you busy? I want to get into this bar.","/str","/ev",{"*":".^.c-4","flg":4},"ev","str","^I need you to help me get into this building.","/str","/ev",{"*":".^.c-5","flg":4},{"c-4":["\n",[["^EVA: Hey, are you busy? I want to get into this bar.","\n",["^HOBO: Yeah, I'm busy. Away you go.","\n","ev","str","^Wait! We can talk this out.","/str","/ev",{"*":".^.c-0","flg":4},"ev","str","^What's more important than getting me inside?","/str","/ev",{"*":".^.c-1","flg":4},{"c-0":["\n",[["^EVA: Wait! We can talk this out.","\n",["^HOBO: The moon is out, missy, it's time for bed.","\n","ev","str","^No, there is so much left for us to do!","/str","/ev",{"*":".^.c-0","flg":4},"ev","str","^If you could get me inside, I would get you some booze.","/str","/ev",{"*":".^.c-1","flg":4},{"c-0":["\n",[["^EVA: No, there is so much left for us to do!","\n",["^HOBO: For example?","\n",["^EVA: For example, party! I am sure a fine minister like you will enjoy some hot food and cool drinks.","\n",["^HOBO: Party?","\n",["^EVA: Yeah, if we can get inside the bar.","\n",{"->":"_interrogation_hobo_is_sus"},{"#f":5,"#n":"g-4"}],{"#f":5,"#n":"g-3"}],{"#f":5,"#n":"g-2"}],{"#f":5,"#n":"g-1"}],{"#f":5,"#n":"g-0"}],null],{"#f":5}],"c-1":["\n",[["^EVA: If you could get me inside, I would get you some booze.","\n",{"->":"_interrogation_pre_alrighty_missy_section"},{"#f":5,"#n":"g-0"}],null],{"#f":5}],"#f":5,"#n":"g-1"}],{"#f":5,"#n":"g-0"}],null],{"#f":5}],"c-1":["\n",[["^EVA: What's more important than getting me inside?","\n",{"->":"_interrogation_why_get_in_there"},{"#f":5,"#n":"g-0"}],null],{"#f":5}],"#f":5,"#n":"g-1"}],{"#f":5,"#n":"g-0"}],null],{"#f":5}],"c-5":["\n",[["^HOBO: Why? Whazz in it for me?","\n","ev","str","^I could get you some food from inside if you'd like.","/str","/ev",{"*":".^.c-0","flg":4},"ev","str","^To be honest with you, nothing.","/str","/ev",{"*":".^.c-1","flg":4},{"c-0":["\n",[["^EVA: I could get you some food from inside if you'd like.","\n",["^HOBO: FOOD? Missy, food ain't gonna cure the hole in my heart that burns for my wife. *cough* Can't believe she left me for that pimp of a man.","\n","ev","str","^What happened with your wife?","/str","/ev",{"*":".^.c-0","flg":4},"ev","str","^As much as I'm sorry about whatever happened to you, I'm sure we can work something out.","/str","/ev",{"*":".^.c-1","flg":4},{"c-0":["^ ",{"->":"_interrogation_what_happened_with_wife"},"\n",{"#f":5}],"c-1":["\n",[["^EVA: As much as I'm sorry about whatever happened to you, I'm sure we can work something out.","\n",["^EVA: NEED TO CONTINUE HERE BUDDY OL' PAL","\n",{"->":"end_interrogation"},{"#f":5,"#n":"g-1"}],{"#f":5,"#n":"g-0"}],null],{"#f":5}],"#f":5,"#n":"g-1"}],{"#f":5,"#n":"g-0"}],null],{"#f":5}],"c-1":["\n",[["^EVA: To be honest with you, nothing.","\n",["^HOBO: HAH! Looong shot then, missy. I ain't helping you.","\n","ev","str","^Please? I really need to get in here.","/str","/ev",{"*":".^.c-0","flg":4},"ev","str","^Look. If you get me in, you can have anything you want out of the back store room after I leave.","/str","/ev",{"*":".^.c-1","flg":4},{"c-0":["\n",[["^EVA: Please? I really need to get in here.","\n",{"->":"_interrogation_why_get_in_there"},{"#f":5,"#n":"g-0"}],null],{"#f":5}],"c-1":["\n",[["^EVA: Look. If you get me in, you can have anything you want out of the back store room after I leave.","\n",["^HOBO: *cough* I dunno if there's anythin' I even want back there!","\n","ev","str","^Right.","/str","/ev",{"*":".^.c-0","flg":4},"ev","str","^It's a bar. There likely is alcohol.","/str","/ev",{"*":".^.c-1","flg":4},{"c-0":["\n",[["^EVA: Right.","\n",["^EVA: NEED TO CONTINUE HERE BUDDY OL' PAL","\n",["^EVA: skill issue ratio l dance dogwater seethe get rekt noobs","\n",{"->":"end_interrogation"},{"#f":5,"#n":"g-2"}],{"#f":5,"#n":"g-1"}],{"#f":5,"#n":"g-0"}],null],{"#f":5}],"c-1":["\n",[["^EVA: It's a bar. There likely is alcohol.","\n",{"->":"_interrogation_alright_missy_section"},{"#f":5,"#n":"g-0"}],null],{"#f":5}],"#f":5,"#n":"g-1"}],{"#f":5,"#n":"g-0"}],null],{"#f":5}],"#f":5,"#n":"g-1"}],{"#f":5,"#n":"g-0"}],null],{"#f":5}],"#f":5,"#n":"g-0"}],null],{"#f":5}],"#f":5}]}],{"#f":1}],"_interrogation_why_get_in_there":[["^HOBO: Why do you wanna get in there?","\n","ev","str","^I have a personal matter to deal with. I advise you not be involved.","/str","/ev",{"*":".^.c-0","flg":4},"ev","str","^I have my reasons, don't ask.","/str","/ev",{"*":".^.c-1","flg":4},{"c-0":["\n",[["^EVA: I have a personal matter to deal with. I advise you not be involved.","\n",["^HOBO: Say, I had a nosy friend who went around butting in all kinds of business. Last time I checked, he is murdered...by a fair lady that looks like you.","\n","ev","str","^What is your point? Are you going to do it or not?","/str","/ev",{"*":".^.c-0","flg":4},"ev","str","^I am sorry to hear about your friend.","/str","/ev",{"*":".^.c-1","flg":4},{"c-0":["\n",[["^HOBO: Woah! Getting aggressive! Do you want to fight? My punches hurts more than anything! *STUMBLES*","\n","ev","str","^Sorry, that's not what I meant. I am simply startled because you mentioned a murder.","/str","/ev",{"*":".^.c-0","flg":4},"ev","str","^I AM NOT AFRAID OF YOU!","/str","/ev",{"*":".^.c-1","flg":4},{"c-0":["\n",[["^EVA: Sorry, that's not what I meant. I am simply startled because you mentioned a murder.","\n",["^HOBO: Why would ya be startled by that missy? Got something to hide?","\n","ev","str","^OF COURSE NOT!","/str","/ev",{"*":".^.c-0","flg":4},"ev","str","^My father murdered...","/str","/ev",{"*":".^.c-1","flg":4},{"c-0":["\n",[["^EVA: OF COURSE NOT!","\n",{"->":"_interrogation_hobo_is_sus"},{"#f":5,"#n":"g-0"}],null],{"#f":5}],"c-1":["\n",[["^EVA: My father murdered...","\n",["^HOBO: Poor missy, you can't possibly have it worst than me. My wife ditched me for another man! That son of a bitch has nothing worthy, don't even know what she was thinking.","\n","ev","str","^You are right, your wife is dumb for leaving you.","/str","/ev",{"*":".^.c-0","flg":4},"ev","str","^My father was a true hero in my life.","/str","/ev",{"*":".^.c-1","flg":4},{"c-0":["\n",[["^EVA: You are right, your wife is dumb for leaving you.","\n",["^HOBO: DON'T TALK ABOUT MY WIFE LIKE that","\n",["^EVA: wait.... this is a dead end???? wha???","\n",["^Programmers: HEY WRITERS YO FINISH THIS SECTION LOL","\n",{"->":"end_interrogation"},{"#f":5,"#n":"g-3"}],{"#f":5,"#n":"g-2"}],{"#f":5,"#n":"g-1"}],{"#f":5,"#n":"g-0"}],null],{"#f":5}],"c-1":["\n",[["^EVA: My father was a true hero in my life. He loved my mother and I with everything he had. If only I can go back in time, I would have done anything to save him.","\n",["^HOBO: Hell, aren't you something.","\n",{"->":"_interrogation_alright_missy_section"},{"#f":5,"#n":"g-1"}],{"#f":5,"#n":"g-0"}],null],{"#f":5}],"#f":5,"#n":"g-1"}],{"#f":5,"#n":"g-0"}],null],{"#f":5}],"#f":5,"#n":"g-1"}],{"#f":5,"#n":"g-0"}],null],{"#f":5}],"c-1":["\n",[["^EVA: I AM NOT AFRAID OF YOU!","\n",{"->":"_interrogation_hobo_is_sus"},{"#f":5,"#n":"g-0"}],null],{"#f":5}],"#f":5,"#n":"g-0"}],null],{"#f":5}],"c-1":["\n",[["^EVA: ... I am sorry to hear about your friend.","\n",["^HOBO: Ya. Me too.","\n","ev","str","^So... could you open the door for me?","/str","/ev",{"*":".^.c-0","flg":4},"ev","str","^You sound like you're from the south. How did you get here?","/str","/ev",{"*":".^.c-1","flg":4},{"c-0":["\n",[["^EVA: So... could you open the door for me?","\n",{"->":"_interrogation_hobo_is_sus"},{"#f":5,"#n":"g-0"}],null],{"#f":5}],"c-1":["^ ",{"->":"_interrogation_from_south"},"\n",{"#f":5}],"#f":5,"#n":"g-1"}],{"#f":5,"#n":"g-0"}],null],{"#f":5}],"#f":5,"#n":"g-1"}],{"#f":5,"#n":"g-0"}],null],{"#f":5}],"c-1":["\n",[["^EVA: I have my reasons, don't ask.","\n",["^HOBO: HA! You remind me of my wife...before she left with that stupid man.","\n",{"->":"_interrogation_what_happened_with_wife"},{"#f":5,"#n":"g-1"}],{"#f":5,"#n":"g-0"}],null],{"#f":5}]}],{"#f":1}],"_interrogation_what_happened_with_wife":[["^EVA: What happened with your wife?","\n","^HOBO: Arghh... somethin' about me not lovin' her enough. She.... she didn't understand that I had to put in a lotta work just to keep the farm alive. I woulda loved her more if I could, but our kids were dyin faster than the crops. Found a new man and off she went.","\n","ev","str","^What happened to the farm?","/str","/ev",{"*":".^.c-0","flg":4},"ev","str","^What happened to your kids?","/str","/ev",{"*":".^.c-1","flg":4},{"c-0":["\n",[["^HOBO: After she was gone, I had no more hope. Sold the farm for twelve cents.","\n","ev","str","^You sound like you're from the south. How did you get here?","/str","/ev",{"*":".^.c-0","flg":4},"ev","str","^Who bought it?","/str","/ev",{"*":".^.c-1","flg":4},{"c-0":["^ ",{"->":"_interrogation_from_south"},"\n",{"#f":5}],"c-1":["\n",[["^EVA: Twelve cents? Who bought it?","\n",["^HOBO: I dunno. Some company. *cough*","\n",["^EVA: I have connections. I can try to help you get back your farm if you help me get into this building.","\n",["^HOBO: Someone like YOU has CONNECTIONS? What are ya, some sorta detective?","\n","ev","str","^Sort of...","/str","/ev",{"*":".^.c-0","flg":4},"ev","str","^Well, not really...","/str","/ev",{"*":".^.c-1","flg":4},{"c-0":["\n",[["^EVA: Sort of...","\n",["^HOBO: Sorta? Shouldn't you have other detectives with ya? Why can't ya get in if you're investigatin'?","\n",["^EVA: So I-","\n",["^HOBO: Are ya part of those guys who swindled me outta my farm? Argh, what does anyting even matter! I need another bottle. But...","\n",{"->":"_interrogation_hobo_is_sus"},{"#f":5,"#n":"g-3"}],{"#f":5,"#n":"g-2"}],{"#f":5,"#n":"g-1"}],{"#f":5,"#n":"g-0"}],null],{"#f":5}],"c-1":["\n",[["^EVA: Well, not really...","\n",["^HOBO: Strange. You kinda remind me of an old detective I read about in the paper years ago! What was his name...? Heard he killed himself, though.","\n","ev","str","^That sounds so sad. I... definitely don't know who that is.","/str","/ev",{"*":".^.c-0","flg":4},"ev","str","^Riiiight... well, back to getting into this bar...","/str","/ev",{"*":".^.c-1","flg":4},{"c-0":["\n",[["^EVA: That sounds so sad. I... definitely don't know who that is.","\n",["^HOBO: ...missy, if I wasn't drunk outta my mind I'da said you paused a lil too long there. Are you... hidin' sumthing?","\n","ev","str","^No, I'm not hiding anything.","/str","/ev",{"*":".^.c-0","flg":4},"ev","str","^Yes. I have things I am not willing to share, and so do you.","/str","/ev",{"*":".^.c-1","flg":4},{"c-0":["\n",[["^EVA: No, I'm not hiding anything.","\n",{"->":"_interrogation_hobo_is_sus"},{"#f":5,"#n":"g-0"}],null],{"#f":5}],"c-1":["\n",[["^EVA: Yes. I have things I am not willing to share, and so do you.","\n",["^HOBO: ...","\n",["^EVA: I don't think we should further this conversation. Look, if you get me into that bar, I'll try to get you some alcohol.","\n",{"->":"_interrogation_pre_alrighty_missy_section"},{"#f":5,"#n":"g-2"}],{"#f":5,"#n":"g-1"}],{"#f":5,"#n":"g-0"}],null],{"#f":5}],"#f":5,"#n":"g-1"}],{"#f":5,"#n":"g-0"}],null],{"#f":5}],"c-1":["\n",[["^EVA: Riiiight... well, back to getting into this bar...","\n",["^HOBO: I like you. Yer not a pryer, not one of those cockeyed sucklers that stole my farm.","\n",{"->":"_interrogation_alright_missy_section"},{"#f":5,"#n":"g-1"}],{"#f":5,"#n":"g-0"}],null],{"#f":5}],"#f":5,"#n":"g-1"}],{"#f":5,"#n":"g-0"}],null],{"#f":5}],"#f":5,"#n":"g-3"}],{"#f":5,"#n":"g-2"}],{"#f":5,"#n":"g-1"}],{"#f":5,"#n":"g-0"}],null],{"#f":5}],"#f":5,"#n":"g-0"}],null],{"#f":5}],"c-1":["\n",[["^EVA: What happened to your kids?","\n",["^HOBO: My- my wife... sold our kids. For two dollars. I dunno where they are...","\n",["^HOBO: Damn it! I hate rememberin'! Fuck you, fuck you, fuck you! *DRINKS ALCOHOL*","\n",{"->":"_interrogation_fail_state"},{"#f":5,"#n":"g-2"}],{"#f":5,"#n":"g-1"}],{"#f":5,"#n":"g-0"}],null],{"#f":5}]}],{"#f":1}],"_interrogation_from_south":["^EVA: You sound like you're from the south. How did you get here?","\n","^HOBO: I walked. Trust me little missy, alcohol lets you do anythin'!","\n","^HOBO: Speaking of, I've sobered up wayyy too much fer my tastes. I hate rememberin'. Good luck with yer thing ya were doin'. *DRINKS ALCOHOL*","\n",{"->":"_interrogation_fail_state"},{"#f":1}],"_interrogation_pre_alrighty_missy_section":["^HOBO: You sure are one direct little lady. I like that about'cha. Too many fake people in this world, all tryna sugar coat how absolute horse manure this world is. And ALCOHOL! That's my favourite word.","\n",{"->":"_interrogation_alright_missy_section"},{"#f":1}],"_interrogation_alright_missy_section":["^HOBO: Alrighty, missy. I'll help ya out. Let me just... urgh...","\n",{"->":"end_interrogation"},{"#f":1}],"_interrogation_hobo_is_sus":["^HOBO: Missy, you are hella fishy. I ain't helping you.","\n",{"->":"_interrogation_fail_state"},{"#f":1}],"_interrogation_fail_state":["^HOBO: *LAYS DOWN AND FALLS ASLEEP*","\n",{"->":"end_interrogation"},{"#f":1}],"save_and_exit":[{"temp=":"address"},"ev",{"VAR?":"address"},"/ev",{"VAR=":"interrogation_1_checkpoint","re":true},{"->":"end_interrogation"},{"#f":1}],"end_interrogation":[{"#":"end"},{"->":"idle"},{"#f":1}],"global decl":["ev",{"^->":"interrogation_1"},{"VAR=":"interrogation_1_checkpoint"},"/ev","end",null],"#f":1}],"listDefs":{}}